bifidotyper/__init__.py
bifidotyper/cli.py
bifidotyper/hmo_genes.py
bifidotyper/logger.py
bifidotyper/plotting.py
bifidotyper/processor.py
bifidotyper/references.py
bifidotyper/sylph.py
bifidotyper/data/bin/sylph_aarch64-any-linux
bifidotyper/data/bin/sylph_arm64-any-darwin
bifidotyper/data/bin/sylph_x86_64-any-darwin
bifidotyper/data/bin/sylph_x86_64-any-linux
bifidotyper/data/reference/CP001095.1_coding_seqs.gb
bifidotyper/data/reference/CP001095.1_gene_sequences.fasta
bifidotyper/data/reference/CP001095.1_genes.bed
bifidotyper/data/reference/CP001095.1_genes.gff3
bifidotyper/data/reference/CP001095.1_genome.fasta
bifidotyper/data/reference/CP001095.1_genome.fasta.fai
bifidotyper/data/reference/bifidobacteria_sketches.syldb
bifidotyper/data/reference/bifidotyper_graphical_abstract.png
bifidotyper/data/reference/genomes.csv
bifidotyper/data/reference/get_gene_sequences.sh
bifidotyper/data/reference/humann2_HMO_annotation.csv
bifidotyper-0.1.2.dist-info/LICENSE
bifidotyper-0.1.2.dist-info/METADATA
bifidotyper-0.1.2.dist-info/WHEEL
bifidotyper-0.1.2.dist-info/entry_points.txt
bifidotyper-0.1.2.dist-info/top_level.txt
bifidotyper-0.1.2.dist-info/RECORD
