Metadata-Version: 2.1
Name: bifidotyper
Version: 0.1.2
Summary: A bioinformatics tool for analyzing Bifidobacteria in sequencing data.
Home-page: https://github.com/Bennibraun/bifidotyper
Author: Ben Braun
Author-email: braun.ben-1@colorado.edu
Classifier: Programming Language :: Python :: 3
Classifier: License :: OSI Approved :: MIT License
Classifier: Operating System :: OS Independent
Requires-Python: >=3.7
License-File: LICENSE
Requires-Dist: numpy
Requires-Dist: pandas
Requires-Dist: seaborn
Requires-Dist: matplotlib
Requires-Dist: tqdm
Requires-Dist: scikit-learn
Requires-Dist: natsort
Requires-Dist: palettable
